ducflair_duc/__init__.py
ducflair_duc/main.py
ducflair_duc-1.15.0.dist-info/METADATA
ducflair_duc-1.15.0.dist-info/WHEEL
ducflair_duc-1.15.0.dist-info/top_level.txt
ducflair_duc-1.15.0.dist-info/RECORD
