Metadata-Version: 2.2
Name: ducflair-duc
Version: 1.15.0
Summary: The duc 2D CAD file format Python implementation
Author-email: Ducflair <support@ducflair.com>
License: MIT
Project-URL: Homepage, https://duc.ducflair.com
Project-URL: Source, https://github.com/ducflair/duc
Classifier: Development Status :: 3 - Alpha
Classifier: Intended Audience :: Developers
Classifier: License :: OSI Approved :: MIT License
Classifier: Programming Language :: Python :: 3
Classifier: Programming Language :: Python :: 3.7
Classifier: Programming Language :: Python :: 3.8
Classifier: Programming Language :: Python :: 3.9
Requires-Python: >=3.7
Requires-Dist: flatbuffers
